franklin_admin/__encrypt.py
franklin_admin/__init__.py
franklin_admin/_encrypt.py
franklin_admin/encrypt.py
franklin_admin/password.py
franklin_admin/users.py
franklin_admin/data/admin/kasper_token.enc
franklin_admin/data/gitui/key_bindings.ron
franklin_admin/data/gitui/key_symbols.ron
franklin_admin/data/gitui/theme.ron
franklin_admin-0.1.36.dist-info/licenses/LICENSE
franklin_admin-0.1.36.dist-info/METADATA
franklin_admin-0.1.36.dist-info/WHEEL
franklin_admin-0.1.36.dist-info/entry_points.txt
franklin_admin-0.1.36.dist-info/top_level.txt
franklin_admin-0.1.36.dist-info/RECORD
