Metadata-Version: 2.4
Name: franklin-admin
Version: 0.1.36
Summary: Administrator plugin for Franklin - adds user management commands
Author-email: Kasper Munch <kaspermunch@birc.au.dk>
Maintainer-email: Kasper Munch <kaspermunch@birc.au.dk>
Project-URL: Homepage, https://munch-group.org/franklin
Project-URL: Documentation, https://munch-group.org/franklin
Project-URL: Repository, https://github.com/munch-group/franklin-admin.git
Project-URL: Issues, https://github.com/munch-group/franklin-admin/issues
Keywords: teaching,jupyter,docker,gitlab
Classifier: Development Status :: 4 - Beta
Classifier: Intended Audience :: Education
Classifier: Topic :: Software Development :: Build Tools
Classifier: Programming Language :: Python :: 3
Classifier: Programming Language :: Python :: 3.9
Classifier: Programming Language :: Python :: 3.10
Classifier: Programming Language :: Python :: 3.11
Classifier: Programming Language :: Python :: 3.12
Classifier: Programming Language :: Python :: 3.13
Requires-Python: >=3.9
License-File: LICENSE
Requires-Dist: franklin-educator>=0.3.140
Dynamic: license-file
